{"cameraMode":{"drawMode":0,"name":"Shaded","section":"Shading Mode"},"sceneLighting":true,"audioPlay":false,"sceneViewState":{"m_AlwaysRefresh":false,"showFog":true,"showSkybox":true,"showFlares":true,"showImageEffects":true,"showParticleSystems":true,"showVisualEffectGraphs":true,"m_FxEnabled":true},"in2DMode":false,"pivot":{"x":0.14576853811740876,"y":1.3763787746429444,"z":-2.6778013706207277},"rotation":{"x":-0.0036198170855641367,"y":0.9923921227455139,"z":-0.030087541788816453,"w":-0.11935955286026001},"size":1.5512124300003052,"orthographic":false}